{
  "no": 704,
  "form": null,
  "name": "ヌメラ",
  "formName": null,
  "status": {
    "hp": 45,
    "attack": 50,
    "defence": 35,
    "spAttack": 55,
    "spDefence": 75,
    "speed": 40
  },
  "type": [{ "typeId": 15,
  "typeName": "ドラゴン"}
],
  "ability": [{ "abilityName": "そうしょく","abilityEffect": "くさタイプのわざを無効化し、こうげきが1段階上がる。", "hidden": false},{ "abilityName": "うるおいボディ","abilityEffect": "あめのとき、状態異常を治す。", "hidden": false},{ "abilityName": "ぬめぬめ","abilityEffect": "直接攻撃を受けたとき、相手のすばやさを1段階下げる。", "hidden": true}],
  "regionId": 6,
  "evolution": ["704", "705", "705-hisui", "706", "706-hisui"]
}