{
  "no": 423,
  "form": null,
  "name": "トリトドン",
  "formName": null,
  "status": {
    "hp": 111,
    "attack": 83,
    "defence": 68,
    "spAttack": 92,
    "spDefence": 82,
    "speed": 39
  },
  "type": [{ "typeId": 3,
  "typeName": "みず"}
,{ "typeId": 9,
  "typeName": "じめん"}
],
  "ability": [{ "abilityName": "ねんちゃく","abilityEffect": "持ち物を奪われない。 つりの成功率が上がる。", "hidden": false},{ "abilityName": "よびみず","abilityEffect": "みずわざの対象を自分にし、無効化してとくこうを1段階上げる。", "hidden": false},{ "abilityName": "すなのちから","abilityEffect": "すなあらしのとき、いわ・じめん・はがねの威力が1.3倍になる。", "hidden": true}],
  "evolution": ["423"]
}